CHANGES.txt
CONTRIBUTORS.txt
README.txt
bootstrap.py
buildout.cfg
setup.py
collective/__init__.py
collective.buildout.cluster.egg-info/PKG-INFO
collective.buildout.cluster.egg-info/SOURCES.txt
collective.buildout.cluster.egg-info/dependency_links.txt
collective.buildout.cluster.egg-info/entry_points.txt
collective.buildout.cluster.egg-info/namespace_packages.txt
collective.buildout.cluster.egg-info/not-zip-safe
collective.buildout.cluster.egg-info/requires.txt
collective.buildout.cluster.egg-info/top_level.txt
collective/buildout/__init__.py
collective/buildout/cluster/README.txt
collective/buildout/cluster/__init__.py
collective/buildout/cluster/async.py
collective/buildout/cluster/base.py
collective/buildout/cluster/client.py
collective/buildout/cluster/cluster.py
collective/buildout/cluster/server.py
collective/buildout/cluster/states.py
collective/buildout/cluster/tests/__init__.py
collective/buildout/cluster/tests/test_docs.py