Metadata-Version: 1.0
Name: collective.buildout.cluster
Version: 0.6
Summary: A package to introspect and manage a buildout-based cluster configuration in an object-oriented way
Home-page: UNKNOWN
Author: Sidnei da Silva
Author-email: sidnei at enfoldsystems dot com
License: LGPL
Keywords: buildout cluster management introspection configuration
Platform: UNKNOWN
Classifier: Framework :: Buildout
Classifier: Intended Audience :: Developers
Classifier: Topic :: Software Development :: Build Tools
Classifier: Topic :: Software Development :: Libraries :: Python Modules
Classifier: License :: OSI Approved :: GNU Library or Lesser General Public License (LGPL)
